MANIFEST.in
README.md
requirements.txt
setup.cfg
setup.py
snn1337/__init__.py
snn1337/connection.py
snn1337/layers.py
snn1337/spiking_from_lasagne.py
snn1337.egg-info/PKG-INFO
snn1337.egg-info/SOURCES.txt
snn1337.egg-info/dependency_links.txt
snn1337.egg-info/requires.txt
snn1337.egg-info/top_level.txt
snn1337/cython/neuron.cpp