Metadata-Version: 1.1
Name: snn1337
Version: 0.0.1
Summary: spiking neural network framework 
Home-page: https://github.com/demikandr/snn1337
Author: snn1337 contributors
Author-email: UNKNOWN
License: MIT
Download-URL: https://github.com/demikandr/snn1337/tarball/0.0.1
Platform: UNKNOWN
Classifier: Development Status :: 3 - Alpha
Classifier: Intended Audience :: Developers
Classifier: Programming Language :: Python :: 3
Classifier: Programming Language :: Python :: 2
